quickinteg/__about__.py
quickinteg/__init__.py
quickinteg/cfg_reader.py
quickinteg/cli.py
quickinteg/excel_shortcut.py
quickinteg/mcd_check.py
quickinteg/processing_logging.py
quickinteg/rop_grace.py
quickinteg/spatialiteio.py
quickinteg/external/__init__.py
quickinteg-2.5.0.dist-info/licenses/LICENSE
quickinteg-2.5.0.dist-info/METADATA
quickinteg-2.5.0.dist-info/WHEEL
quickinteg-2.5.0.dist-info/entry_points.txt
quickinteg-2.5.0.dist-info/top_level.txt
quickinteg-2.5.0.dist-info/RECORD
