Metadata-Version: 2.4
Name: quickinteg
Version: 2.5.0
Summary: Scripts QGIS Processing pour l'intégration rapide des données.
Author: Valérian LEBERT
License: GPL-3.0-or-later
Project-URL: Homepage, https://gitlab.com/vlebert/quickinteg/
Project-URL: Repository, https://gitlab.com/vlebert/quickinteg/
Keywords: QGIS,processing,spatial,data,integration
Classifier: Development Status :: 4 - Beta
Classifier: Intended Audience :: Developers
Classifier: License :: OSI Approved :: GNU General Public License v3 or later (GPLv3+)
Classifier: Programming Language :: Python :: 3
Classifier: Programming Language :: Python :: 3.9
Classifier: Topic :: Scientific/Engineering :: GIS
Requires-Python: >=3.9
License-File: LICENSE
Requires-Dist: xlsxwriter==3.1.9
Requires-Dist: openpyxl==3.1.2
Provides-Extra: dev
Requires-Dist: ruff>=0.8.0; extra == "dev"
Requires-Dist: basedpyright>=1.21; extra == "dev"
Dynamic: license-file
